 [
    {
        "barcode": "171102555",
        "dpc": "03010247801",
        "name": "សៅ  មន្ថា"
    },
        {
            "barcode": "171102556",
            "dpc": "03010247701",
            "name": "សៅ  ហ៊ាល"
        },
        {
            "barcode": "171102557",
            "dpc": "03010247601",
            "name": "គឹម  ផាត់"
        },
        {
            "barcode": "171102558",
            "dpc": "03010247401",
            "name": "ស៊ាង  ចាន់ធាម"
        },
        {
            "barcode": "171102559",
            "dpc": "03010247201",
            "name": "ញ៉ែម  សុខា"
        },
        {
            "barcode": "171102560",
            "dpc": "03010247101",
            "name": "អោក  ប៊ុនធឿន"
        },
        {
            "barcode": "171102561",
            "dpc": "03010244301",
            "name": "តាន់  សារឿន"
        },
        {
            "barcode": "171102562",
            "dpc": "03010242001",
            "name": "សុខ  ធឿន"
        },
        {
            "barcode": "171102563",
            "dpc": "03010241501",
            "name": "សុខ  ឃាង"
        },
        {
            "barcode": "171102564",
            "dpc": "03010238601",
            "name": "ជុំ  សុខុម"
        },
        {
            "barcode": "171102565",
            "dpc": "03010238501",
            "name": "សុខ  ចាន់"
        },
        {
            "barcode": "171102566",
            "dpc": "03010236901",
            "name": "តាំង  ប៊ុនហ៊ីម"
        },
        {
            "barcode": "171102567",
            "dpc": "03010236301",
            "name": "ខៀវ  សំហេន"
        },
        {
            "barcode": "171102568",
            "dpc": "03010235201",
            "name": "ផូ  ធូរេន"
        },
        {
            "barcode": "171102569",
            "dpc": "03010234401",
            "name": "យឹម  សុខា"
        },
        {
            "barcode": "171102570",
            "dpc": "03010233601",
            "name": "ថង សៀង"
        },
        {
            "barcode": "171102571",
            "dpc": "03010229501",
            "name": "ឈុន  ស្រេង"
        },
        {
            "barcode": "171102572",
            "dpc": "03010226301",
            "name": "ឌួង វិបុល"
        },
        {
            "barcode": "171102573",
            "dpc": "03010220901",
            "name": "ជាង  ម៉េត"
        },
        {
            "barcode": "171102574",
            "dpc": "03010216701",
            "name": "ឈិន  វណ្ណដា ២"
        },
        {
            "barcode": "171102575",
            "dpc": "03010207001",
            "name": "រ៉ាយ  សារ៉ុម"
        },
        {
            "barcode": "171102576",
            "dpc": "03010204301",
            "name": "ហ៊ាន  ហឹម"
        },
        {
            "barcode": "171102577",
            "dpc": "03010204501",
            "name": "ជួង ខ្វា"
        },
        {
            "barcode": "171102578",
            "dpc": "03010204601",
            "name": "កែវ សៀប៉ូ"
        },
        {
            "barcode": "171102579",
            "dpc": "03010204201",
            "name": "សន ប៊ុនធឿន"
        },
        {
            "barcode": "171102580",
            "dpc": "03010204001",
            "name": "សុក ពុធ"
        },
        {
            "barcode": "171102581",
            "dpc": "03010203901",
            "name": "ថន សារិទ្ធ"
        },
        {
            "barcode": "171102582",
            "dpc": "03010203801",
            "name": "ជយ ហឿម"
        },
        {
            "barcode": "171102583",
            "dpc": "03010203501",
            "name": "សូ ឈឿងលី"
        },
        {
            "barcode": "171102584",
            "dpc": "03010203601",
            "name": "ផូ សុងហេង"
        },
        {
            "barcode": "171102585",
            "dpc": "03010203701",
            "name": "សុផល"
        },
        {
            "barcode": "171102586",
            "dpc": "03010247301",
            "name": "សួន ចាន់សឿន"
        },
        {
            "barcode": "171102587",
            "dpc": "03010247901",
            "name": "ជុន ណៃឈឿត"
        },
        {
            "barcode": "171102588",
            "dpc": "03010247501",
            "name": "គុយ ឈុំណាត"
        },
        {
            "barcode": "171102589",
            "dpc": "03010200301",
            "name": "ចាន់ តុន"
        },
        {
            "barcode": "171102590",
            "dpc": "03010200201",
            "name": "នូវ ខន្តី"
        },
        {
            "barcode": "171102591",
            "dpc": "03010200101",
            "name": "ឡាច សាមឿន"
        },
        {
            "barcode": "171102592",
            "dpc": "03010201601",
            "name": "លឿម សុខហេង"
        },
        {
            "barcode": "171102593",
            "dpc": "03010202201",
            "name": "ពុម ប៊ុនង៉ា"
        },
        {
            "barcode": "171102594",
            "dpc": "03010202301",
            "name": "ហេង ស៊ុនហូរ"
        },
        {
            "barcode": "171102595",
            "dpc": "03010202401",
            "name": "សៅ ណាវី"
        },
        {
            "barcode": "171102596",
            "dpc": "03010200601",
            "name": "កេត្រ ចន្ត្រា"
        },
        {
            "barcode": "171102597",
            "dpc": "03010200701",
            "name": "កែវ ដេត"
        },
        {
            "barcode": "171102598",
            "dpc": "03010202101",
            "name": "ហូរ ធី"
        },
        {
            "barcode": "171102599",
            "dpc": "03010202001",
            "name": "យ៉ន បូរ៉ា"
        },
        {
            "barcode": "171102600",
            "dpc": "03010201901",
            "name": "អួង ណារ៉េត"
        },
        {
            "barcode": "171102601",
            "dpc": "03010201801",
            "name": "ហឿង ហាយ"
        },
        {
            "barcode": "171102602",
            "dpc": "03010201701",
            "name": "ប៊ិន យួម"
        },
        {
            "barcode": "171102603",
            "dpc": "03010201501",
            "name": "សេង សុភី"
        },
        {
            "barcode": "171102604",
            "dpc": "03010201401",
            "name": "កុយ នុយ"
        },
        {
            "barcode": "171102605",
            "dpc": "03010201301",
            "name": "យ៉ាត ស្រីសុខុម"
        },
        {
            "barcode": "171102606",
            "dpc": "03010201201",
            "name": "យឹម យឿន"
        },
        {
            "barcode": "171102607",
            "dpc": "03010201101",
            "name": "កេត្រ ស៊ីយ៉ារ៉ា"
        },
        {
            "barcode": "171102608",
            "dpc": "03010201001",
            "name": "សារ័ត្ន មុន្នី"
        },
        {
            "barcode": "171102609",
            "dpc": "03010200901",
            "name": "យិន ពៅ"
        },
        {
            "barcode": "171102610",
            "dpc": "03010200801",
            "name": "ម៉ី សារី"
        },
        {
            "barcode": "171102611",
            "dpc": "03010200401",
            "name": "ប៉ូវ សំភី"
        },
        {
            "barcode": "171102612",
            "dpc": "03010203401",
            "name": "វ៉ន ណារ៉ូ"
        },
        {
            "barcode": "171102613",
            "dpc": "03010203301",
            "name": "ហេង សុភាព"
        },
        {
            "barcode": "171102614",
            "dpc": "03010203001",
            "name": "ជា វណ្ណៈ"
        },
        {
            "barcode": "171102615",
            "dpc": "03010203101",
            "name": "ម៉ែន សុខុម"
        },
        {
            "barcode": "171102616",
            "dpc": "03010202801",
            "name": "រៀន សំណាង"
        },
        {
            "barcode": "171102617",
            "dpc": "03010202701",
            "name": "គឹម សាន្ត"
        },
        {
            "barcode": "171102618",
            "dpc": "03010202601",
            "name": "ថន ប៊ុនថាន់"
        },
        {
            "barcode": "171102619",
            "dpc": "03010242801",
            "name": "សង ថន"
        },
        {
            "barcode": "171102620",
            "dpc": "03010243001",
            "name": "មន្ទីរពេទ្យសុខសាន"
        },
        {
            "barcode": "171102621",
            "dpc": "03010243201",
            "name": "ឌុក សាង"
        },
        {
            "barcode": "171102622",
            "dpc": "03010243301",
            "name": "នាង ឡានី"
        },
        {
            "barcode": "171102623",
            "dpc": "03010243401",
            "name": "សំ ឆន"
        },
        {
            "barcode": "171102624",
            "dpc": "03010243501",
            "name": "ម៉េង សុគិត"
        },
        {
            "barcode": "171102625",
            "dpc": "03010243601",
            "name": "ម៉េង សុឡាតា"
        },
        {
            "barcode": "171102626",
            "dpc": "03010243701",
            "name": "តាន់ ម៉េង"
        },
        {
            "barcode": "171102627",
            "dpc": "03010242301",
            "name": "ប៉ុក ណាវី"
        },
        {
            "barcode": "171102628",
            "dpc": "03010242401",
            "name": "ហ៊ុយ យិនង៉"
        },
        {
            "barcode": "171102629",
            "dpc": "03010242501",
            "name": "ហោ គឹមសឿង"
        },
        {
            "barcode": "171102630",
            "dpc": "03010242601",
            "name": "ម៉ម សុម៉ាវត្តី"
        },
        {
            "barcode": "171102631",
            "dpc": "03010242701",
            "name": "អ៊ុក មិត្ត"
        },
        {
            "barcode": "171102632",
            "dpc": "03010245901",
            "name": "ម៉ាក់ សុខា"
        },
        {
            "barcode": "171102633",
            "dpc": "03010245801",
            "name": "ប៊ុន ប្រសិទ្ធ"
        },
        {
            "barcode": "171102634",
            "dpc": "03010246001",
            "name": "ឡុង ផលគុន"
        },
        {
            "barcode": "171102635",
            "dpc": "03010246101",
            "name": "ប៉ាន់  ហូ"
        },
        {
            "barcode": "171102636",
            "dpc": "03010246201",
            "name": "ផាន់ សុគឿន"
        },
        {
            "barcode": "171102637",
            "dpc": "03010246301",
            "name": "សៀ គឹមណៃ"
        },
        {
            "barcode": "171102638",
            "dpc": "03010246401",
            "name": "សៀ ប៊ុនយឺ"
        },
        {
            "barcode": "171102639",
            "dpc": "03010244001",
            "name": "លួត ភួង"
        },
        {
            "barcode": "171102640",
            "dpc": "03010244101",
            "name": "អៀក ភៀង"
        },
        {
            "barcode": "171102641",
            "dpc": "03010244201",
            "name": "អៀក ឈៀត"
        },
        {
            "barcode": "171102642",
            "dpc": "03010244401",
            "name": "អៀប រិននឿត"
        },
        {
            "barcode": "171102643",
            "dpc": "03010244501",
            "name": "ស៊ុត សឿង"
        },
        {
            "barcode": "171102644",
            "dpc": "03010244601",
            "name": "ភន រដ្ឋា"
        },
        {
            "barcode": "171102645",
            "dpc": "03010244801",
            "name": "លួង ឆយ"
        },
        {
            "barcode": "171102646",
            "dpc": "03010244901",
            "name": "ប៉ិច ហាប់"
        },
        {
            "barcode": "171102647",
            "dpc": "03010245001",
            "name": "ប៉ិច ប៉ុក"
        },
        {
            "barcode": "171102648",
            "dpc": "03010245101",
            "name": "ប៉េ ហួម"
        },
        {
            "barcode": "171102649",
            "dpc": "03010245201",
            "name": "ដូង  រតនះ"
        },
        {
            "barcode": "171102650",
            "dpc": "03010245301",
            "name": "ទេព ទូ"
        },
        {
            "barcode": "171102651",
            "dpc": "03010245401",
            "name": "នុល ឈឿង"
        },
        {
            "barcode": "171102652",
            "dpc": "03010245501",
            "name": "អៀង សម្បត្តិ"
        },
        {
            "barcode": "171102653",
            "dpc": "03010245601",
            "name": "ប៊ូ ប៉ុច"
        },
        {
            "barcode": "171102654",
            "dpc": "03010245701",
            "name": "ឌុច ហឿម"
        },
        {
            "barcode": "171102655",
            "dpc": "03010241701",
            "name": "ចំរើ រដ្ឋ"
        },
    {
        "barcode": "171102656",
        "dpc": "03010241801",
        "name": "សោម មាន"
    },
    {
        "barcode": "171102657",
        "dpc": "03010241301",
        "name": "វត្តសង្កែ"
    },
    {
        "barcode": "171102658",
        "dpc": "03010243801",
        "name": "ស៊ុប ធី (វត្តសង្កែ)"
    },
    {
        "barcode": "171102659",
        "dpc": "03010241001",
        "name": "ចាន់ គឹមហុង"
    },
    {
        "barcode": "171102660",
        "dpc": "03010240901",
        "name": "ផាន់ សុវណ្ណ"
    },
    {
        "barcode": "171102661",
        "dpc": "03010241101",
        "name": "សំ សុវណ្ណ"
    },
    {
        "barcode": "171102662",
        "dpc": "03010241201",
        "name": "ឆេង ស្រីនាថ"
    },
    {
        "barcode": "171102663",
        "dpc": "03010241401",
        "name": "សោម សុវណ្ណ"
    },
    {
        "barcode": "171102664",
        "dpc": "03010241601",
        "name": "ឯម សុភាព"
    },
    {
        "barcode": "171102665",
        "dpc": "03010242101",
        "name": "ចាន់ ថុលឡា"
    },
    {
        "barcode": "171102666",
        "dpc": "03010241901",
        "name": "សួន សុខន"
    },
    {
        "barcode": "171102667",
        "dpc": "03010246701",
        "name": "ប៉ិល សៃ"
    },
    {
        "barcode": "171102668",
        "dpc": "03010246801",
        "name": "តុល ចាន់សុខ"
    },
    {
        "barcode": "171102669",
        "dpc": "03010238101",
        "name": "ចាន ធូ"
    },
    {
        "barcode": "171102670",
        "dpc": "03010238201",
        "name": "ហ៊ាង រ័ត្ន"
    },
    {
        "barcode": "171102671",
        "dpc": "03010238401",
        "name": "នាង ផល្លា"
    },
    {
        "barcode": "171102672",
        "dpc": "03010238301",
        "name": "ចាន់ សារឿម"
    },
    {
        "barcode": "171102673",
        "dpc": "03010238701",
        "name": "កែវ សាឡាត់"
    },
    {
        "barcode": "171102674",
        "dpc": "03010240401",
        "name": "អ៊ិន ស៊ីដារ៉េ"
    },
    {
        "barcode": "171102675",
        "dpc": "03010240501",
        "name": "ជា ឆន"
    },
    {
        "barcode": "171102676",
        "dpc": "03010240601",
        "name": "ម៉ី វណ្ណទូច"
    },
    {
        "barcode": "171102677",
        "dpc": "03010240801",
        "name": "ពៅ ពីដារិទ្ធ"
    },
    {
        "barcode": "171102678",
        "dpc": "03010238801",
        "name": "ឯក សុផាន"
    },
    {
        "barcode": "171102679",
        "dpc": "03010238901",
        "name": "ហួយ ប៊ុនឡេង"
    },
    {
        "barcode": "171102680",
        "dpc": "03010246601",
        "name": "ស សារិន"
    },
    {
        "barcode": "171102681",
        "dpc": "03010246901",
        "name": "យិន នូ"
    },
    {
        "barcode": "171102682",
        "dpc": "03010236601",
        "name": "ជា ហុង"
    },
    {
        "barcode": "171102683",
        "dpc": "03010236501",
        "name": "វ៉ា គឹមអូន"
    },
    {
        "barcode": "171102684",
        "dpc": "03010236401",
        "name": "ម៉ម ហ៊ីម"
    },
    {
        "barcode": "171102685",
        "dpc": "03010237301",
        "name": "ប៊ុន  ប៉ា"
    },
    {
        "barcode": "171102686",
        "dpc": "03010237401",
        "name": "ឯក សំអូន ១"
    },
    {
        "barcode": "171102687",
        "dpc": "03010237501",
        "name": "ឯក សំអូន ៣"
    },
    {
        "barcode": "171102688",
        "dpc": "03010237601",
        "name": "អូន វិបុល"
    },
    {
        "barcode": "171102689",
        "dpc": "03010237801",
        "name": "អ៊ុក វី"
    },
    {
        "barcode": "171102690",
        "dpc": "03010240101",
        "name": "ព្រហ្ម មរណៈ"
    },
    {
        "barcode": "171102691",
        "dpc": "03010237901",
        "name": "មួង រ៉េន"
    },
    {
        "barcode": "171102692",
        "dpc": "03010238001",
        "name": "សោ បូរិទ្ធ"
    },
    {
        "barcode": "171102693",
        "dpc": "03010236701",
        "name": "ស្វិត ជេដ្ឋា"
    },
    {
        "barcode": "171102694",
        "dpc": "03010236801",
        "name": "ស៊ុត សៅរ៉ាន"
    },
    {
        "barcode": "171102695",
        "dpc": "03010237001",
        "name": "ភោគ សុផុន ២"
    },
    {
        "barcode": "171102696",
        "dpc": "03010237101",
        "name": "ឡុច ឈឿត"
    },
    {
        "barcode": "171102697",
        "dpc": "03010237201",
        "name": "អ៊ឹង ពោធិរដ្ឋ"
    },
    {
        "barcode": "171102698",
        "dpc": "03010237701",
        "name": "ព្រហ្ម មរណៈ"
    },
    {
        "barcode": "171102699",
        "dpc": "03010239201",
        "name": "លឹម ហូរ"
    },
    {
        "barcode": "171102700",
        "dpc": "03010240201",
        "name": "ម៉េង វ៉ានដានីន"
    },
    {
        "barcode": "171102701",
        "dpc": "03010240301",
        "name": "ហ៊ុល ធី"
    },
    {
        "barcode": "171102702",
        "dpc": "03010239101",
        "name": "ផុន សាវឿន"
    },
    {
        "barcode": "171102703",
        "dpc": "03010239301",
        "name": "ចាយ តុងកឹង"
    },
    {
        "barcode": "171102704",
        "dpc": "03010239401",
        "name": "សូ ភីយា"
    },
    {
        "barcode": "171102705",
        "dpc": "03010239501",
        "name": "សៀ បេន"
    },
    {
        "barcode": "171102706",
        "dpc": "03010239601",
        "name": "រស់ សុធី"
    },
    {
        "barcode": "171102707",
        "dpc": "03010239701",
        "name": "ឃួន ឈឿត ១"
    },
    {
        "barcode": "171102708",
        "dpc": "03010239901",
        "name": "ឃួន ឈឿត ៣"
    },
    {
        "barcode": "171102709",
        "dpc": "03010239801",
        "name": "ឃួន ឈឿត ២"
    },
    {
        "barcode": "171102710",
        "dpc": "03010240001",
        "name": "ឈឿន វេង"
    },
    {
        "barcode": "171102711",
        "dpc": "03010232501",
        "name": "សេង សាវុធ"
    },
    {
        "barcode": "171102712",
        "dpc": "03010232601",
        "name": "លក ស៊ូ"
    },
    {
        "barcode": "171102713",
        "dpc": "03010232701",
        "name": "ពិន សុជាតា"
    },
    {
        "barcode": "171102714",
        "dpc": "03010232801",
        "name": "សុ វណ្ណារី"
    },
    {
        "barcode": "171102715",
        "dpc": "03010232901",
        "name": "សាយ សុវណ្ណរ៉េត"
    },
    {
        "barcode": "171102716",
        "dpc": "03010233001",
        "name": "ហុក ដាវិន"
    },
    {
        "barcode": "171102717",
        "dpc": "03010233101",
        "name": "ថេត ថេន"
    },
    {
        "barcode": "171102718",
        "dpc": "03010233301",
        "name": "តាំង អ៊ិចហុង"
    },
    {
        "barcode": "171102719",
        "dpc": "03010233401",
        "name": "ជី"
    },
    {
        "barcode": "171102720",
        "dpc": "03010233501",
        "name": "ជា ស៊ីមៀន"
    },
    {
        "barcode": "171102721",
        "dpc": "03010233801",
        "name": "ឈាង ហាក់"
    },
    {
        "barcode": "171102722",
        "dpc": "03010233901",
        "name": "អៀ សាវុធ"
    },
    {
        "barcode": "171102723",
        "dpc": "03010234001",
        "name": "គី ឌីណា"
    },
    {
        "barcode": "171102724",
        "dpc": "03010234101",
        "name": "ឃួន ស៊ីម៉ង"
    },
    {
        "barcode": "171102725",
        "dpc": "03010234201",
        "name": "ប៉ែន សារិទ្ធ"
    },
    {
        "barcode": "171102726",
        "dpc": "03010234301",
        "name": "ទិត្យ ហ៊ាន"
    },
    {
        "barcode": "171102727",
        "dpc": "03010234501",
        "name": "ទស្ស ហុង"
    },
    {
        "barcode": "171102728",
        "dpc": "03010234601",
        "name": "ឡាញ សាអូន"
    },
    {
        "barcode": "171102729",
        "dpc": "03010234701",
        "name": "ឡាំ គឹមហេង"
    },
    {
        "barcode": "171102730",
        "dpc": "03010234801",
        "name": "ចេង សុខណា"
    },
    {
        "barcode": "171102731",
        "dpc": "03010235001",
        "name": "អ៊ឹង ឆាយ"
    },
    {
        "barcode": "171102732",
        "dpc": "03010235101",
        "name": "ហ៊ាង រ៉ាវុត"
    },
    {
        "barcode": "171102733",
        "dpc": "03010235301",
        "name": "យ៉ុន ធារិទ្ធ"
    },
    {
        "barcode": "171102734",
        "dpc": "03010235401",
        "name": "ព្រះវិហារ"
    },
    {
        "barcode": "171102735",
        "dpc": "03010235501",
        "name": "ខាន់ ម៉ាណេ"
    },
    {
        "barcode": "171102736",
        "dpc": "03010235601",
        "name": "ឡុង ផលគុណ"
    },
    {
        "barcode": "171102737",
        "dpc": "03010235701",
        "name": "មួង សារ៉េន ១"
    },
    {
        "barcode": "171102738",
        "dpc": "03010235801",
        "name": "នឹម សួ"
    },
    {
        "barcode": "171102739",
        "dpc": "03010231601",
        "name": "ពេជ្រ ព្រហ្មមុនី"
    },
    {
        "barcode": "171102740",
        "dpc": "03010231701",
        "name": "សួង សុធា"
    },
    {
        "barcode": "171102741",
        "dpc": "03010231801",
        "name": "សួង ចាន់ទី"
    },
    {
        "barcode": "171102742",
        "dpc": "03010231901",
        "name": "សួង សុគន្ធ"
    },
    {
        "barcode": "171102743",
        "dpc": "03010232001",
        "name": "សោ វុទ្ធី"
    },
    {
        "barcode": "171102744",
        "dpc": "03010232101",
        "name": "ទេព វិត"
    },
    {
        "barcode": "171102745",
        "dpc": "03010232201",
        "name": "ជ័យ សែន"
    },
    {
        "barcode": "171102746",
        "dpc": "03010232301",
        "name": "តេង ហុកហេង"
    },
    {
        "barcode": "171102747",
        "dpc": "03010232401",
        "name": "អ៊ុយ វណ្ណនី"
    },
    {
        "barcode": "171102748",
        "dpc": "03010231201",
        "name": "ខៀវ សុជាតិ"
    },
    {
        "barcode": "171102749",
        "dpc": "03010230901",
        "name": "សុខ វីរៈ"
    },
    {
        "barcode": "171102750",
        "dpc": "03010230701",
        "name": "ទាត់ ធឿន"
    },
    {
        "barcode": "171102751",
        "dpc": "03010230601",
        "name": "ហម អនុជ"
    },
    {
        "barcode": "171102752",
        "dpc": "03010230501",
        "name": "ឡេង ហ៊ន"
    },
    {
        "barcode": "171102753",
        "dpc": "03010230301",
        "name": "ជា ដាលីន"
    },
    {
        "barcode": "171102754",
        "dpc": "03010230401",
        "name": "ភួង ភិរ័ត្ន"
    },
    {
        "barcode": "171102755",
        "dpc": "03010230101",
        "name": "ហ៊ុល ហេង"
    },
    {
        "barcode": "171102756",
        "dpc": "03010230001",
        "name": "យូ ឈឿម"
    },
    {
        "barcode": "171102757",
        "dpc": "03010230201",
        "name": "វង្ស វ៉ាន"
    },
    {
        "barcode": "171102758",
        "dpc": "03010231001",
        "name": "ឡាំង វង្ស"
    },
    {
        "barcode": "171102759",
        "dpc": "03010231301",
        "name": "ជី នី"
    },
    {
        "barcode": "171102760",
        "dpc": "03010231401",
        "name": "ឯម វរិទ្ធ"
    },
    {
        "barcode": "171102761",
        "dpc": "03010229601",
        "name": "រ៉ាយ ប៊ុនធឿន"
    },
    {
        "barcode": "171102762",
        "dpc": "03010229401",
        "name": "ប៉ោ ទ្រីឌឿន ១"
    },
    {
        "barcode": "171102763",
        "dpc": "03010229301",
        "name": "ប៉ោ ទ្រីឌឿន ២"
    },
    {
        "barcode": "171102764",
        "dpc": "03010229201",
        "name": "គង់ បាន ២"
    },
    {
        "barcode": "171102765",
        "dpc": "03010229101",
        "name": "ងួន រតនៈ"
    },
    {
        "barcode": "171102766",
        "dpc": "03010229001",
        "name": "សុក វិត"
    },
    {
        "barcode": "171102767",
        "dpc": "03010228901",
        "name": "អ៊ឹង វឌ្ឍនៈ"
    },
    {
        "barcode": "171102768",
        "dpc": "03010228401",
        "name": "ណឹម ប៉េកាឡេ"
    },
    {
        "barcode": "171102769",
        "dpc": "03010228701",
        "name": "មាស វិចិត្រ"
    },
    {
        "barcode": "171102770",
        "dpc": "03010228601",
        "name": "ខឹម សុភា"
    },
    {
        "barcode": "171102771",
        "dpc": "03010228801",
        "name": "វែន សុភ័ក្រ្ត"
    },
    {
        "barcode": "171102772",
        "dpc": "03010229901",
        "name": "ឈឹម ទឹម"
    },
    {
        "barcode": "171102773",
        "dpc": "03010229801",
        "name": "សាន់ លីហ៊ាង"
    },
    {
        "barcode": "171102774",
        "dpc": "03010229701",
        "name": "អ៊ុក សាមឿន"
    },
    {
        "barcode": "171102775",
        "dpc": "03010228301",
        "name": "អៀង សេរី"
    },
    {
        "barcode": "171102776",
        "dpc": "03010228201",
        "name": "អេង ង៉ោ"
    },
    {
        "barcode": "171102777",
        "dpc": "03010228101",
        "name": "ជុង សុចិត្រា"
    },
    {
        "barcode": "171102778",
        "dpc": "03010228001",
        "name": "គី ប៊ុនណាល់"
    },
    {
        "barcode": "171102779",
        "dpc": "03010227901",
        "name": "ឈាង សែ"
    },
    {
        "barcode": "171102780",
        "dpc": "03010227801",
        "name": "ញ៉ែម ចាន់នី"
    },
    {
        "barcode": "171102781",
        "dpc": "03010227601",
        "name": "ជួប សាវឿន"
    },
    {
        "barcode": "171102782",
        "dpc": "03010227501",
        "name": "ជួន ស្រីមុំ"
    },
    {
        "barcode": "171102783",
        "dpc": "03010227701",
        "name": "លឹម ហ៊ួសាន"
    },
    {
        "barcode": "171102784",
        "dpc": "03010227401",
        "name": "មាស ទុំ"
    },
    {
        "barcode": "171102785",
        "dpc": "03010227301",
        "name": "សេង ដាន់ណា"
    },
    {
        "barcode": "171102786",
        "dpc": "03010224501",
        "name": "អួន គុណ"
    },
    {
        "barcode": "171102787",
        "dpc": "03010227101",
        "name": "នង សាមឿន"
    },
    {
        "barcode": "171102788",
        "dpc": "03010227001",
        "name": "សូ កូវីតា​ (មុខ)"
    },
    {
        "barcode": "171102789",
        "dpc": "03010226701",
        "name": "គង់ ម៉ៅ"
    },
    {
        "barcode": "171102790",
        "dpc": "03010226801",
        "name": "មាស សារុន"
    },
    {
        "barcode": "171102791",
        "dpc": "03010226501",
        "name": "សួស ស៊ីណាន"
    },
    {
        "barcode": "171102792",
        "dpc": "03010226401",
        "name": "ទ្រឿង ល័ក្ខ"
    },
    {
        "barcode": "171102793",
        "dpc": "03010226201",
        "name": "ភិន សាមឿន ៤"
    },
    {
        "barcode": "171102794",
        "dpc": "03010226101",
        "name": "ភិន សាមឿន 3"
    },
    {
        "barcode": "171102795",
        "dpc": "03010226001",
        "name": "ភិន សាមឿន ២"
    },
    {
        "barcode": "171102796",
        "dpc": "03010225901",
        "name": "ភិន សាមឿន ១"
    },
    {
        "barcode": "171102797",
        "dpc": "03010225801",
        "name": "ប៉ូ វិវឌ្ឍនៈ"
    },
    {
        "barcode": "171102798",
        "dpc": "03010225701",
        "name": "វ៉ៃ ប៉ូ"
    },
    {
        "barcode": "171102799",
        "dpc": "03010225601",
        "name": "លី រ៉ូវីដា"
    },
    {
        "barcode": "171102800",
        "dpc": "03010225501",
        "name": "សេក ម៉ាលីស"
    },
    {
        "barcode": "171102801",
        "dpc": "03010225301",
        "name": "ប៉ែន សាវុធ"
    },
    {
        "barcode": "171102802",
        "dpc": "03010225201",
        "name": "អ៊ឹង សារី"
    },
    {
        "barcode": "171102803",
        "dpc": "03010225101",
        "name": "សឿន សុភី"
    },
    {
        "barcode": "171102804",
        "dpc": "03010225001",
        "name": "យ៉ម ចំរើន ៥"
    },
    {
        "barcode": "171102805",
        "dpc": "03010224901",
        "name": "យ៉ម ចំរើន ៣"
    },
    {
        "barcode": "171102806",
        "dpc": "03010224801",
        "name": "ហេង មន្នីចិន្តា"
    },
    {
        "barcode": "171102807",
        "dpc": "03010224701",
        "name": "ទិស្នាក់ការ"
    },
    {
        "barcode": "171102808",
        "dpc": "03010224601",
        "name": "គង់ ឡៃហាន់"
    },
    {
        "barcode": "171102809",
        "dpc": "03010224401",
        "name": "ហ៊ាង ប៊ុនហុក"
    },
    {
        "barcode": "171102810",
        "dpc": "03010224301",
        "name": "ជា បូ"
    },
    {
        "barcode": "171102811",
        "dpc": "03010224201",
        "name": "កុយ ហ៊ាង"
    },
    {
        "barcode": "171102812",
        "dpc": "03010224101",
        "name": "កាំង ឈីវឃៀម"
    },
    {
        "barcode": "171102813",
        "dpc": "03010224001",
        "name": "ញ៉ែម យ៉ានី"
    },
    {
        "barcode": "171102814",
        "dpc": "03010223901",
        "name": "ប៉ិច ដារ៉ារិទ្ធ"
    },
    {
        "barcode": "171102815",
        "dpc": "03010223701",
        "name": "ប៉ែន រដ្ឋា"
    },
    {
        "barcode": "171102816",
        "dpc": "03010223401",
        "name": "អ៊ួន សុក"
    },
    {
        "barcode": "171102817",
        "dpc": "03010223601",
        "name": "វ៉ាន សុខុម"
    },
    {
        "barcode": "171102818",
        "dpc": "03010223201",
        "name": "រ៉ុង សាឌីន"
    },
    {
        "barcode": "171102819",
        "dpc": "03010223301",
        "name": "សុង រ៉ាវាល់ពិនឌី"
    },
    {
        "barcode": "171102820",
        "dpc": "03010223501",
        "name": "ព្រាប ផន"
    },
    {
        "barcode": "171102821",
        "dpc": "03010223101",
        "name": "ពី ឈន"
    },
    {
        "barcode": "171102822",
        "dpc": "03010222901",
        "name": "ឃួយ  ស៊ីម៉ុង"
    },
    {
        "barcode": "171102823",
        "dpc": "03010222701",
        "name": "ស៊ុយ សាវុធ"
    },
    {
        "barcode": "171102824",
        "dpc": "03010222601",
        "name": "ខឹម ស៊ីផាត"
    },
    {
        "barcode": "171102825",
        "dpc": "03010222801",
        "name": "ប៊ុន សាំង"
    },
    {
        "barcode": "171102826",
        "dpc": "03010221101",
        "name": "សុខ ហេង"
    },
    {
        "barcode": "171102827",
        "dpc": "03010221201",
        "name": "ទូច  ញិប"
    },
    {
        "barcode": "171102828",
        "dpc": "03010221401",
        "name": "ឈុន លី"
    },
    {
        "barcode": "171102829",
        "dpc": "03010221501",
        "name": "ប៊ុន លាង"
    },
    {
        "barcode": "171102830",
        "dpc": "03010221601",
        "name": "ប៊ុន ហៀង"
    },
    {
        "barcode": "171102831",
        "dpc": "03010221801",
        "name": "ស៊ុត សឿង"
    },
    {
        "barcode": "171102832",
        "dpc": "03010221701",
        "name": "ខា ខូយ"
    },
    {
        "barcode": "171102833",
        "dpc": "03010222101",
        "name": "កៅ ស៊ាន"
    },
    {
        "barcode": "171102834",
        "dpc": "03010221901",
        "name": "ញ៉ិល  ច្រិច"
    },
    {
        "barcode": "171102835",
        "dpc": "03010222201",
        "name": "អ៊ាប ជីម៉ាន់"
    },
    {
        "barcode": "171102836",
        "dpc": "03010222501",
        "name": "តាំង ឡូយ"
    },
    {
        "barcode": "171102837",
        "dpc": "03010213201",
        "name": "លឹម អ៊ីនស្រ៊ុន"
    },
    {
        "barcode": "171102838",
        "dpc": "03010213301",
        "name": "សេង យីវ"
    },
    {
        "barcode": "171102839",
        "dpc": "03010213401",
        "name": "អ៊ិន តាប់"
    },
    {
        "barcode": "171102840",
        "dpc": "03010213501",
        "name": "ដែង សុវណ្ណ"
    },
    {
        "barcode": "171102841",
        "dpc": "03010213701",
        "name": "អ៊ាង វុទ្ធី"
    },
    {
        "barcode": "171102842",
        "dpc": "03010213801",
        "name": "តន់ តូច"
    },
    {
        "barcode": "171102843",
        "dpc": "03010213901",
        "name": "លឿង យីវ"
    },
    {
        "barcode": "171102844",
        "dpc": "03010214201",
        "name": "សឹង វិសាល"
    },
    {
        "barcode": "171102845",
        "dpc": "03010214301",
        "name": "ពុញ ឆៃ"
    },
    {
        "barcode": "171102846",
        "dpc": "03010214401",
        "name": "ហម ឆាយ"
    },
    {
        "barcode": "171102847",
        "dpc": "03010214501",
        "name": "ផ្កាយ ភីណែ"
    },
    {
        "barcode": "171102848",
        "dpc": "03010214601",
        "name": "ទុយ ចិន្តា"
    },
    {
        "barcode": "171102849",
        "dpc": "03010214701",
        "name": "គង់ ស៊ីណាត"
    },
    {
        "barcode": "171102850",
        "dpc": "03010214801",
        "name": "ជៀម  ផារុំ"
    },
    {
        "barcode": "171102851",
        "dpc": "03010214901",
        "name": "គឹម ចាន់ធូ"
    },
    {
        "barcode": "171102852",
        "dpc": "03010215001",
        "name": "ហួត  លី"
    },
    {
        "barcode": "171102853",
        "dpc": "03010215201",
        "name": "នៅ ស៊ីយឿប"
    },
    {
        "barcode": "171102854",
        "dpc": "03010215301",
        "name": "អ៊ិន សេង"
    },
    {
        "barcode": "171102855",
        "dpc": "03010215401",
        "name": "ឡេង មួយ"
    },
    {
        "barcode": "171102856",
        "dpc": "03010215501",
        "name": "អៀង សុភៀង"
    },
    {
        "barcode": "171102857",
        "dpc": "03010215601",
        "name": "វង្ស ឡេង"
    },
    {
        "barcode": "171102858",
        "dpc": "03010215701",
        "name": "គឹម សារ៉ន"
    },
    {
        "barcode": "171102859",
        "dpc": "03010215801",
        "name": "សុខ ធឿន"
    },
    {
        "barcode": "171102860",
        "dpc": "03010216001",
        "name": "នាង ឯល"
    },
    {
        "barcode": "171102861",
        "dpc": "03010216201",
        "name": "គឹម ជាតិ"
    },
    {
        "barcode": "171102862",
        "dpc": "03010216401",
        "name": "សេស សុខុម"
    },
    {
        "barcode": "171102863",
        "dpc": "03010216501",
        "name": "អ៊ូច សុផល"
    },
    {
        "barcode": "171102864",
        "dpc": "03010216601",
        "name": "ហ៊ិន សំរេច"
    },
    {
        "barcode": "171102865",
        "dpc": "03010216101",
        "name": "ឈិន វណ្ណដា"
    },
    {
        "barcode": "171102866",
        "dpc": "03010216801",
        "name": "សុខ សុវណ្ណ"
    },
    {
        "barcode": "171102867",
        "dpc": "03010216901",
        "name": "ជាង ឡេង"
    },
    {
        "barcode": "171102868",
        "dpc": "03010217001",
        "name": "សុខ ស៊ីវង្ស"
    },
    {
        "barcode": "171102869",
        "dpc": "03010217101",
        "name": "លឹម លីហឿប"
    },
    {
        "barcode": "171102870",
        "dpc": "03010217301",
        "name": "វង្ស យិន"
    },
    {
        "barcode": "171102871",
        "dpc": "03010217501",
        "name": "វ៉ន ឌៀប"
    },
    {
        "barcode": "171102872",
        "dpc": "03010217701",
        "name": "ចាន់ អាយ"
    },
    {
        "barcode": "171102873",
        "dpc": "03010217801",
        "name": "អ៊ុង សុភាព"
    },
    {
        "barcode": "171102874",
        "dpc": "03010217901",
        "name": "ឡៃ ហ៊ាង"
    },
    {
        "barcode": "171102875",
        "dpc": "03010218001",
        "name": "ចៅ ហ៊ាង"
    },
    {
        "barcode": "171102876",
        "dpc": "03010218101",
        "name": "ឈូក  វណ្ណស៊ី"
    },
    {
        "barcode": "171102877",
        "dpc": "03010218201",
        "name": "យ៉ម ចំរើន ៦"
    },
    {
        "barcode": "171102878",
        "dpc": "03010218301",
        "name": "លឹម សារ៉ែម"
    },
    {
        "barcode": "171102879",
        "dpc": "03010218501",
        "name": "គិត ឆដា"
    },
    {
        "barcode": "171102880",
        "dpc": "03010218601",
        "name": "សាំង លាភ"
    },
    {
        "barcode": "171102881",
        "dpc": "03010218701",
        "name": "សាន់ ផាន់ណា"
    },
    {
        "barcode": "171102882",
        "dpc": "03010218801",
        "name": "ចិន អមរា"
    },
    {
        "barcode": "171102883",
        "dpc": "03010219001",
        "name": "ទេស ស៊ី"
    },
    {
        "barcode": "171102884",
        "dpc": "03010219101",
        "name": "ទេស មាន"
    },
    {
        "barcode": "171102885",
        "dpc": "03010219201",
        "name": "វ៉ាត ពង់"
    },
    {
        "barcode": "171102886",
        "dpc": "03010219301",
        "name": "ឈឿង គឹមសុង"
    },
    {
        "barcode": "171102887",
        "dpc": "03010219401",
        "name": "ស គឹមប៉ូ"
    },
    {
        "barcode": "171102888",
        "dpc": "03010219501",
        "name": "ស៊ិន ហេង"
    },
    {
        "barcode": "171102889",
        "dpc": "03010219601",
        "name": "សាន ហោ"
    },
    {
        "barcode": "171102890",
        "dpc": "03010219701",
        "name": "ហេង កៅ"
    },
    {
        "barcode": "171102891",
        "dpc": "03010219801",
        "name": "ស៊ឹម អឿន"
    },
    {
        "barcode": "171102892",
        "dpc": "03010219901",
        "name": "សំរិត នូ"
    },
    {
        "barcode": "171102893",
        "dpc": "03010220001",
        "name": "ភេង អង"
    },
    {
        "barcode": "171102894",
        "dpc": "03010220201",
        "name": "ស៊ុន រ៉ន"
    },
    {
        "barcode": "171102895",
        "dpc": "03010220301",
        "name": "ខុង ខន"
    },
    {
        "barcode": "171102896",
        "dpc": "03010220401",
        "name": "អេង ណារ៉ុង"
    },
    {
        "barcode": "171102897",
        "dpc": "03010220601",
        "name": "លន ប៊ុនឈន"
    },
    {
        "barcode": "171102898",
        "dpc": "03010220701",
        "name": "ស៊ុន ស៊ុយ"
    },
    {
        "barcode": "171102899",
        "dpc": "03010220801",
        "name": "ឡុង វ៉ាង"
    },
    {
        "barcode": "171102900",
        "dpc": "03010221001",
        "name": "ប៊ុត ធូ"
    },
    {
        "barcode": "171102901",
        "dpc": "03010231501",
        "name": "សូម កុសល"
    },
    {
        "barcode": "171102902",
        "dpc": "03010236001",
        "name": "ហោ ភិរុណ"
    },
    {
        "barcode": "171102903",
        "dpc": "03010235901",
        "name": "គង់ សារឿន"
    },
    {
        "barcode": "171102904",
        "dpc": "03010236101",
        "name": "ម៉ៅ ង៉ាវ"
    },
    {
        "barcode": "171102905",
        "dpc": "03010236201",
        "name": "ទី លីនដូ"
    },
    {
        "barcode": "171102906",
        "dpc": "03010206801",
        "name": "ថ្លាង ថារេត"
    },
    {
        "barcode": "171102907",
        "dpc": "03010206701",
        "name": "ជយ ហាង"
    },
    {
        "barcode": "171102908",
        "dpc": "03010206601",
        "name": "សេង ហឺ"
    },
    {
        "barcode": "171102909",
        "dpc": "03010206501",
        "name": "ឆាយ ទូច"
    },
    {
        "barcode": "171102910",
        "dpc": "03010206401",
        "name": "ម្លប់ ឆាត់"
    },
    {
        "barcode": "171102911",
        "dpc": "03010206301",
        "name": "ម្លប់ស្បូវម៉ាលី"
    },
    {
        "barcode": "171102912",
        "dpc": "03010206201",
        "name": "ជាម ដារ៉ា"
    },
    {
        "barcode": "171102913",
        "dpc": "03010206101",
        "name": "ឡុង សេរីវុឌ្ឍៈ"
    },
    {
        "barcode": "171102914",
        "dpc": "03010205901",
        "name": "នាក ជា"
    },
    {
        "barcode": "171102915",
        "dpc": "03010206001",
        "name": "នួន ស្នា"
    },
    {
        "barcode": "171102916",
        "dpc": "03010205701",
        "name": "ភន ជិន"
    },
    {
        "barcode": "171102917",
        "dpc": "03010205801",
        "name": "តាំង ឈាងហួរ"
    },
    {
        "barcode": "171102918",
        "dpc": "03010208001",
        "name": "ប៉ា ប៊ុនហាង"
    },
    {
        "barcode": "171102919",
        "dpc": "03010207801",
        "name": "ខាត់ បូរិន"
    },
    {
        "barcode": "171102920",
        "dpc": "03010207701",
        "name": "លី សុផល"
    },
    {
        "barcode": "171102921",
        "dpc": "03010207601",
        "name": "ឃួន ឈាន"
    },
    {
        "barcode": "171102922",
        "dpc": "03010207501",
        "name": "ចៅ ឈីវី"
    },
    {
        "barcode": "171102923",
        "dpc": "03010207401",
        "name": "អឿន សារុន"
    },
    {
        "barcode": "171102924",
        "dpc": "03010207301",
        "name": "ចាន់ ធឿន"
    },
    {
        "barcode": "171102925",
        "dpc": "03010207201",
        "name": "ស្រស់ សារ៉ុម"
    },
    {
        "barcode": "171102926",
        "dpc": "03010207101",
        "name": "តូច អេង"
    },
    {
        "barcode": "171102927",
        "dpc": "03010208601",
        "name": "ណុប សាម៉ន"
    },
    {
        "barcode": "171102928",
        "dpc": "03010208401",
        "name": "ហៀង ហាញ់"
    },
    {
        "barcode": "171102929",
        "dpc": "03010208301",
        "name": "ម៉ៅ ម៉ន"
    },
    {
        "barcode": "171102930",
        "dpc": "03010208101",
        "name": "នួន សាន"
    },
    {
        "barcode": "171102931",
        "dpc": "03010205601",
        "name": "សាម គា"
    },
    {
        "barcode": "171102932",
        "dpc": "03010205501",
        "name": "សៀង សុផល"
    },
    {
        "barcode": "171102933",
        "dpc": "03010205401",
        "name": "ព្រំ សៀង"
    },
    {
        "barcode": "171102934",
        "dpc": "03010205101",
        "name": "តូវ ហូវ"
    },
    {
        "barcode": "171102935",
        "dpc": "03010205301",
        "name": "គង់ សុខឃាង"
    },
    {
        "barcode": "171102936",
        "dpc": "03010205201",
        "name": "អ៊ាន រឿន"
    },
    {
        "barcode": "171102937",
        "dpc": "03010205001",
        "name": "ស្រេង ហេង"
    },
    {
        "barcode": "171102938",
        "dpc": "03010204901",
        "name": "ញ៉ែម ផៃ"
    },
    {
        "barcode": "171102939",
        "dpc": "03010204801",
        "name": "គី វៀត"
    },
    {
        "barcode": "171102940",
        "dpc": "03010204701",
        "name": "ហ៊ី ពិសិទ្ធ"
    },
    {
        "barcode": "171102941",
        "dpc": "03010209201",
        "name": "ប៉ូ ខេងរ៉ន"
    },
    {
        "barcode": "171102942",
        "dpc": "03010209101",
        "name": "ឆុង ហ៊ី"
    },
    {
        "barcode": "171102943",
        "dpc": "03010208901",
        "name": "សោម ជឿង"
    },
    {
        "barcode": "171102944",
        "dpc": "03010208701",
        "name": "ងិន វ៉ារី"
    },
    {
        "barcode": "171102945",
        "dpc": "03010208801",
        "name": "អ៊ាន លី"
    },
    {
        "barcode": "171102946",
        "dpc": "03010210401",
        "name": "កើត យុថា"
    },
    {
        "barcode": "171102947",
        "dpc": "03010210201",
        "name": "អ៊ិត ហៃ"
    },
    {
        "barcode": "171102948",
        "dpc": "03010210001",
        "name": "អាត់ រ៉ាឌី"
    },
    {
        "barcode": "171102949",
        "dpc": "03010209901",
        "name": "វ៉ាន់ ឡុញ"
    },
    {
        "barcode": "171102950",
        "dpc": "03010209801",
        "name": "ត្រឹង ឆាយ"
    },
    {
        "barcode": "171102951",
        "dpc": "03010209701",
        "name": "ត្រឹង ឆោម"
    },
    {
        "barcode": "171102952",
        "dpc": "03010209601",
        "name": "ឃុន ឧត្តម"
    },
    {
        "barcode": "171102953",
        "dpc": "03010209501",
        "name": "នេត សុវណ្ណ"
    },
    {
        "barcode": "171102954",
        "dpc": "03010209401",
        "name": "ហួត សុហេង"
    },
    {
        "barcode": "171102955",
        "dpc": "03010209301",
        "name": "វង្ស វៀត"
    },
    {
        "barcode": "171102956",
        "dpc": "03010212201",
        "name": "ឆេង ពៅ"
    },
    {
        "barcode": "171102957",
        "dpc": "03010211801",
        "name": "កៅ សារ៉េត"
    },
    {
        "barcode": "171102958",
        "dpc": "03010212601",
        "name": "យិន ឡាំ"
    },
    {
        "barcode": "171102959",
        "dpc": "03010212501",
        "name": "យៀវ យ៉ុត"
    },
    {
        "barcode": "171102960",
        "dpc": "03010212401",
        "name": "ស៊ឹម លឹម"
    },
    {
        "barcode": "171102961",
        "dpc": "03010212301",
        "name": "ម៉ៅ មួន"
    },
    {
        "barcode": "171102962",
        "dpc": "03010212101",
        "name": "ស្រេង គឹមស្រេង"
    },
    {
        "barcode": "171102963",
        "dpc": "03010212001",
        "name": "គួច ប៊ុនលី"
    },
    {
        "barcode": "171102964",
        "dpc": "03010211901",
        "name": "ប៊ុន គង់"
    },
    {
        "barcode": "171102965",
        "dpc": "03010211701",
        "name": "នាង ចន្ធី"
    },
    {
        "barcode": "171102966",
        "dpc": "03010211601",
        "name": "ពេជ្រ ណូរ៉ែម"
    },
    {
        "barcode": "171102967",
        "dpc": "03010211201",
        "name": "ឡាយ ផាន្នី"
    },
    {
        "barcode": "171102968",
        "dpc": "03010211101",
        "name": "យស់ សំបឿន"
    },
    {
        "barcode": "171102969",
        "dpc": "03010211501",
        "name": "ប៊ុត ធូ"
    },
    {
        "barcode": "171102970",
        "dpc": "03010211001",
        "name": "អឿ ផាន"
    },
    {
        "barcode": "171102971",
        "dpc": "03010210901",
        "name": "សៅ ទេពសត្ថា"
    },
    {
        "barcode": "171102972",
        "dpc": "03010210801",
        "name": "ជា សរ"
    },
    {
        "barcode": "171102973",
        "dpc": "03010210701",
        "name": "លាង ធារី"
    },
    {
        "barcode": "171102974",
        "dpc": "03010210601",
        "name": "ម៉ុង ចាន់សារ័ត្ន"
    },
    {
        "barcode": "171102975",
        "dpc": "03010210501",
        "name": "វ៉ាន វង្ស"
    },
    {
        "barcode": "171102976",
        "dpc": "03010212901",
        "name": "ទិត សុខា ២"
    },
    {
        "barcode": "171102977",
        "dpc": "03010212701",
        "name": "អោម ផល្លា"
    },
    {
        "barcode": "171102978",
        "dpc": "03010213001",
        "name": "សុខ គុណរិទ្ធ"
    },
    {
        "barcode": "171102979",
        "dpc": "03010239001",
        "name": "ថង សារ៉េត"
    },
    {
        "barcode": "171104342",
        "dpc": "03010224401",
        "name": "ហ៊ាង ប៊ុនហុក"
    },
    {
        "barcode": "171109501",
        "dpc": "03010248001",
        "name": "ម៉ី ជឿន"
    }
    ]
